nileredquant/__init__.py
nileredquant/analyse.py
nileredquant/qc.py
nileredquant/standard_curve.py
nileredquant/utils.py
nileredquant-0.2.2.dist-info/METADATA
nileredquant-0.2.2.dist-info/WHEEL
nileredquant-0.2.2.dist-info/licenses/LICENSE
nileredquant-0.2.2.dist-info/RECORD
