Metadata-Version: 2.4
Name: nileredquant
Version: 0.2.2
Summary: Tool for automated quantification of lipid accumulation in yeasts based on the Nile Red plate assay
Project-URL: Homepage, https://github.com/zganjarmia/NileRedQuant
Project-URL: Repository, https://github.com/zganjarmia/NileRedQuant
Project-URL: Issues, https://github.com/zganjarmia/NileRedQuant/issues
Author-email: Mia Žganjar <zganjar.mia@gmail.com>
Maintainer-email: Mia Žganjar <zganjar.mia@gmail.com>
License: SPDX-License-Identifier: MIT License
License-File: LICENSE
Keywords: HTS,Nile Red,fluorescence,lipid,plate assay,plate reader,yeast
Classifier: Development Status :: 3 - Alpha
Classifier: Intended Audience :: Science/Research
Classifier: License :: OSI Approved :: MIT License
Classifier: Natural Language :: English
Classifier: Operating System :: OS Independent
Classifier: Programming Language :: Python :: 3
Classifier: Programming Language :: Python :: 3 :: Only
Classifier: Programming Language :: Python :: 3.9
Classifier: Programming Language :: Python :: 3.10
Classifier: Programming Language :: Python :: 3.11
Classifier: Topic :: Scientific/Engineering
Classifier: Topic :: Scientific/Engineering :: Bio-Informatics
Classifier: Topic :: Scientific/Engineering :: Chemistry
Classifier: Topic :: Scientific/Engineering :: Information Analysis
Requires-Python: <3.12,>=3.9
Requires-Dist: matplotlib>=3.8.0
Requires-Dist: openpyxl>=3.1.2
Requires-Dist: pandas>=2.2.0
Requires-Dist: pingouin>=0.5.3
Requires-Dist: scipy>=1.11.4
Provides-Extra: dev
Requires-Dist: black; extra == 'dev'
Requires-Dist: build; extra == 'dev'
Requires-Dist: mypy; extra == 'dev'
Requires-Dist: pytest; extra == 'dev'
Requires-Dist: pytest-cov; extra == 'dev'
Requires-Dist: ruff; extra == 'dev'
Requires-Dist: twine; extra == 'dev'
Provides-Extra: docs
Requires-Dist: myst-parser; extra == 'docs'
Requires-Dist: sphinx-autobuild; extra == 'docs'
Requires-Dist: sphinx>=7; extra == 'docs'
